ror/__init__.py
ror/controlers/__init__.py
ror/controlers/common/__init__.py
ror/controlers/common/base_controller.py
ror/schemas/__init__.py
ror/schemas/common/__init__.py
ror/schemas/common/artifact_schema.py
ror/schemas/common/base_schema.py
ror/schemas/fields/__init__.py
ror/schemas/fields/field_perishable.py
ror/schemas/fields/field_persistance.py
ror/stages/__init__.py
ror/stages/common/__init__.py
ror/stages/common/i_base_stage.py
ror/stages/i_forward_stage.py
ror/stages/i_init_stage.py
ror/stages/i_terminal_stage.py
ror/utils/__init__.py
ror/utils/_const.py
ror-0.1.1.dist-info/LICENSE
ror-0.1.1.dist-info/METADATA
ror-0.1.1.dist-info/WHEEL
ror-0.1.1.dist-info/RECORD
