Metadata-Version: 2.1
Name: ror
Version: 0.1.1
Summary: Simple pipelining framework in Python
Home-page: https://patricktourniaire.github.io/ror
Keywords: machine-learning,pipelines,data-processing
Author: Patrick Tourniaire
Author-email: patrick@tourniaire.net
Requires-Python: >=3.8.1,<4.0
Classifier: Programming Language :: Python :: 3
Classifier: Programming Language :: Python :: 3.9
Classifier: Programming Language :: Python :: 3.10
Classifier: Programming Language :: Python :: 3.11
Classifier: Programming Language :: Python :: 3.12
Requires-Dist: rich (>=13.5.2,<14.0.0)
Project-URL: Documentation, https://patricktourniaire.github.io/ror/api_reference/ror.html
Project-URL: Repository, https://github.com/PatrickTourniaire/ror
